{
  "nightly": {
    "description": "Every commit to develop",
    "hide": false,
    "last_updated": "2025-08-16T17:13:14.000Z",
    "last_updated_url": "https://github.com/hotio/qbitmanage/actions/runs/17010887412",
    "latest": false,
    "tags": [
      "nightly",
      "nightly-bb0b48cec4adf675126e9a7d545036a755f894bb",
      "nightly-e8c8cdf"
    ]
  },
  "release": {
    "description": "Releases",
    "hide": false,
    "last_updated": "2025-08-09T01:04:53.000Z",
    "last_updated_url": "https://github.com/hotio/qbitmanage/actions/runs/16843553348",
    "latest": true,
    "tags": [
      "release",
      "release-4.5.3",
      "release-acbe79b"
    ]
  }
}
