{
  "nightly": {
    "description": "Every commit to develop",
    "hide": false,
    "last_updated": "2025-08-04T15:17:34.000Z",
    "last_updated_url": "https://github.com/hotio/qbitmanage/actions/runs/16727073523",
    "latest": false,
    "tags": [
      "nightly",
      "nightly-e2f279a1413853aa0538eabac5f1493d7aec93db",
      "nightly-85c45ba"
    ]
  },
  "release": {
    "description": "Releases",
    "hide": false,
    "last_updated": "2025-08-03T19:17:37.000Z",
    "last_updated_url": "https://github.com/hotio/qbitmanage/actions/runs/16708502903",
    "latest": true,
    "tags": [
      "release",
      "release-4.5.2",
      "release-76b427c"
    ]
  }
}
