{
  "nightly": {
    "description": "Every commit to develop",
    "hide": false,
    "last_updated": "2025-08-18T22:30:57.000Z",
    "last_updated_url": "https://github.com/hotio/qbitmanage/actions/runs/17054083636",
    "latest": false,
    "tags": [
      "nightly",
      "nightly-ad67821f62974b3807cb982fb215e36b31080a5b",
      "nightly-6bb2f4a"
    ]
  },
  "release": {
    "description": "Releases",
    "hide": false,
    "last_updated": "2025-08-17T18:45:17.000Z",
    "last_updated_url": "https://github.com/hotio/qbitmanage/actions/runs/17024451282",
    "latest": true,
    "tags": [
      "release",
      "release-4.5.4",
      "release-2f8d657"
    ]
  }
}
